pydoctor/__init__.py
pydoctor/cli.py
pydoctor/reporter.py
pydoctor/utils.py
pydoctor/parsers/__init__.py
pydoctor/parsers/pyproject_parser.py
pydoctor/parsers/requirements_parser.py
pydoctor/scanner/__init__.py
pydoctor/scanner/dependencies.py
pydoctor/scanner/python_version.py
pydoctor/scanner/system_libs.py
pydoctor/scanner/venv.py
pyenv_doctor-0.1.0.dist-info/licenses/LICENSE
pyenv_doctor-0.1.0.dist-info/METADATA
pyenv_doctor-0.1.0.dist-info/WHEEL
pyenv_doctor-0.1.0.dist-info/entry_points.txt
pyenv_doctor-0.1.0.dist-info/top_level.txt
pyenv_doctor-0.1.0.dist-info/RECORD
