Metadata-Version: 2.4
Name: pyenv-doctor
Version: 0.1.0
Summary: Diagnose Python environment issues and suggest fixes
Home-page: https://github.com/AMEER-ROSHAN/pyenv-doctor
Author: Ameer Roshan H
Author-email: ameerroshan02@gmail.com
Classifier: Programming Language :: Python :: 3
Classifier: License :: OSI Approved :: MIT License
Classifier: Operating System :: OS Independent
Requires-Python: >=3.8
License-File: LICENSE
Requires-Dist: packaging
Requires-Dist: tomli; python_version < "3.11"
Dynamic: author
Dynamic: author-email
Dynamic: classifier
Dynamic: description
Dynamic: description-content-type
Dynamic: home-page
Dynamic: license-file
Dynamic: requires-dist
Dynamic: requires-python
Dynamic: summary
